usdm_osb_uploader/__init__.py
usdm_osb_uploader/cli.py
usdm_osb_uploader/settings.py
usdm_osb_uploader/osb/activities.py
usdm_osb_uploader/osb/arms.py
usdm_osb_uploader/osb/create_study.py
usdm_osb_uploader/osb/criteria.py
usdm_osb_uploader/osb/download_usdm.py
usdm_osb_uploader/osb/elements.py
usdm_osb_uploader/osb/epochs.py
usdm_osb_uploader/osb/high_level_design.py
usdm_osb_uploader/osb/objectivies_endpoints.py
usdm_osb_uploader/osb/osb_api.py
usdm_osb_uploader/osb/population.py
usdm_osb_uploader/osb/soa.py
usdm_osb_uploader/osb/visits.py
usdm_osb_uploader-0.1.0.dist-info/METADATA
usdm_osb_uploader-0.1.0.dist-info/WHEEL
usdm_osb_uploader-0.1.0.dist-info/entry_points.txt
usdm_osb_uploader-0.1.0.dist-info/licenses/LICENSE
usdm_osb_uploader-0.1.0.dist-info/RECORD
