Metadata-Version: 2.4
Name: usdm-osb-uploader
Version: 0.1.0
Summary: Add your description here
Author-email: H Chekresh <hosbectchekresh@gmail.com>
License-File: LICENSE
Requires-Python: >=3.13
Requires-Dist: cyclopts>=3.24.0
Requires-Dist: httpx>=0.28.1
Requires-Dist: pydantic-settings>=2.10.1
Requires-Dist: rich>=13.0.0
